setup.py
wrenet/__init__.py
wrenet/__main__.py
wrenet/wrenet.py
wrenet.egg-info/PKG-INFO
wrenet.egg-info/SOURCES.txt
wrenet.egg-info/dependency_links.txt
wrenet.egg-info/entry_points.txt
wrenet.egg-info/requires.txt
wrenet.egg-info/top_level.txt