Metadata-Version: 1.1
Name: wrenet
Version: 1.1
Summary: Network configurations viewer in the Windows Registry
Home-page: https://github.com/graypawn/wrenet
Author: graypawn
Author-email: choi.pawn@gmail.com
License: Apache License (2.0)
Platform: UNKNOWN
Classifier: Programming Language :: Python
Classifier: Programming Language :: Python :: 3
Classifier: Operating System :: POSIX :: Linux
Classifier: License :: OSI Approved :: Apache Software License
